health_checker/__init__.py
health_checker/health_checker.py
health_checker/network_health.py
health_checker/system_health.py
check_health-0.1.0.dist-info/METADATA
check_health-0.1.0.dist-info/WHEEL
check_health-0.1.0.dist-info/top_level.txt
check_health-0.1.0.dist-info/RECORD
