Metadata-Version: 2.1
Name: check-health
Version: 0.1.0
Summary: A Python package for monitoring health checks of programs.
Author: Fateme Samandarnejad
Author-email: fsamandarnejad2001@gmail.com
Classifier: Programming Language :: Python :: 3
Classifier: License :: OSI Approved :: MIT License
Classifier: Operating System :: OS Independent
Requires-Python: >=3.6
Requires-Dist: psutil >=6.1.0
